{
    "plays": [
        {
            "__play_name": "Resolve host patterns",
            "name": "Resolve host patterns",
            "pattern": "all",
            "play": "Resolve host patterns",
            "play_pattern": "all",
            "play_uuid": "e244a718-1036-a17e-453c-000000000016",
            "playbook": "/root/RH294-9.0/projects-host/playbook3.yml",
            "playbook_uuid": "3e390883-b027-4c8e-b51e-490be5eedb72",
            "tasks": [
                {
                    "__changed": false,
                    "__duration": "0s",
                    "__host": "srv1.example.com",
                    "__number": 0,
                    "__result": "Ok",
                    "__task": "Display managed hosts matching the host pattern",
                    "__task_action": "ansible.builtin.debug",
                    "duration": 0.034299,
                    "end": "2023-03-28T11:01:41.564604",
                    "event_loop": null,
                    "host": "srv1.example.com",
                    "play": "Resolve host patterns",
                    "play_pattern": "all",
                    "play_uuid": "e244a718-1036-a17e-453c-000000000016",
                    "playbook": "/root/RH294-9.0/projects-host/playbook3.yml",
                    "playbook_uuid": "3e390883-b027-4c8e-b51e-490be5eedb72",
                    "remote_addr": "srv1.example.com",
                    "res": {
                        "_ansible_no_log": null,
                        "_ansible_verbose_always": true,
                        "changed": false,
                        "msg": "srv1.example.com"
                    },
                    "resolved_action": "ansible.builtin.debug",
                    "start": "2023-03-28T11:01:41.530305",
                    "task": "Display managed hosts matching the host pattern",
                    "task_action": "ansible.builtin.debug",
                    "task_args": "",
                    "task_path": "/root/RH294-9.0/projects-host/playbook3.yml:6",
                    "task_uuid": "e244a718-1036-a17e-453c-000000000018",
                    "uuid": "f4205961-f5d0-49ab-8563-d38acd732fc7"
                },
                {
                    "__changed": false,
                    "__duration": "0s",
                    "__host": "srv2.example.com",
                    "__number": 1,
                    "__result": "Ok",
                    "__task": "Display managed hosts matching the host pattern",
                    "__task_action": "ansible.builtin.debug",
                    "duration": 0.036435,
                    "end": "2023-03-28T11:01:41.578652",
                    "event_loop": null,
                    "host": "srv2.example.com",
                    "play": "Resolve host patterns",
                    "play_pattern": "all",
                    "play_uuid": "e244a718-1036-a17e-453c-000000000016",
                    "playbook": "/root/RH294-9.0/projects-host/playbook3.yml",
                    "playbook_uuid": "3e390883-b027-4c8e-b51e-490be5eedb72",
                    "remote_addr": "srv2.example.com",
                    "res": {
                        "_ansible_no_log": null,
                        "_ansible_verbose_always": true,
                        "changed": false,
                        "msg": "srv2.example.com"
                    },
                    "resolved_action": "ansible.builtin.debug",
                    "start": "2023-03-28T11:01:41.542217",
                    "task": "Display managed hosts matching the host pattern",
                    "task_action": "ansible.builtin.debug",
                    "task_args": "",
                    "task_path": "/root/RH294-9.0/projects-host/playbook3.yml:6",
                    "task_uuid": "e244a718-1036-a17e-453c-000000000018",
                    "uuid": "952058c2-b158-4190-907c-54a83e9ec22b"
                },
                {
                    "__changed": false,
                    "__duration": "0s",
                    "__host": "s1.lab.example.com",
                    "__number": 2,
                    "__result": "Ok",
                    "__task": "Display managed hosts matching the host pattern",
                    "__task_action": "ansible.builtin.debug",
                    "duration": 0.034113,
                    "end": "2023-03-28T11:01:41.592961",
                    "event_loop": null,
                    "host": "s1.lab.example.com",
                    "play": "Resolve host patterns",
                    "play_pattern": "all",
                    "play_uuid": "e244a718-1036-a17e-453c-000000000016",
                    "playbook": "/root/RH294-9.0/projects-host/playbook3.yml",
                    "playbook_uuid": "3e390883-b027-4c8e-b51e-490be5eedb72",
                    "remote_addr": "s1.lab.example.com",
                    "res": {
                        "_ansible_no_log": null,
                        "_ansible_verbose_always": true,
                        "changed": false,
                        "msg": "s1.lab.example.com"
                    },
                    "resolved_action": "ansible.builtin.debug",
                    "start": "2023-03-28T11:01:41.558848",
                    "task": "Display managed hosts matching the host pattern",
                    "task_action": "ansible.builtin.debug",
                    "task_args": "",
                    "task_path": "/root/RH294-9.0/projects-host/playbook3.yml:6",
                    "task_uuid": "e244a718-1036-a17e-453c-000000000018",
                    "uuid": "b8545678-9eaa-415e-8266-db8a2ca6e38b"
                },
                {
                    "__changed": false,
                    "__duration": "0s",
                    "__host": "s2.lab.example.com",
                    "__number": 3,
                    "__result": "Ok",
                    "__task": "Display managed hosts matching the host pattern",
                    "__task_action": "ansible.builtin.debug",
                    "duration": 0.050675,
                    "end": "2023-03-28T11:01:41.624397",
                    "event_loop": null,
                    "host": "s2.lab.example.com",
                    "play": "Resolve host patterns",
                    "play_pattern": "all",
                    "play_uuid": "e244a718-1036-a17e-453c-000000000016",
                    "playbook": "/root/RH294-9.0/projects-host/playbook3.yml",
                    "playbook_uuid": "3e390883-b027-4c8e-b51e-490be5eedb72",
                    "remote_addr": "s2.lab.example.com",
                    "res": {
                        "_ansible_no_log": null,
                        "_ansible_verbose_always": true,
                        "changed": false,
                        "msg": "s2.lab.example.com"
                    },
                    "resolved_action": "ansible.builtin.debug",
                    "start": "2023-03-28T11:01:41.573722",
                    "task": "Display managed hosts matching the host pattern",
                    "task_action": "ansible.builtin.debug",
                    "task_args": "",
                    "task_path": "/root/RH294-9.0/projects-host/playbook3.yml:6",
                    "task_uuid": "e244a718-1036-a17e-453c-000000000018",
                    "uuid": "91b975fc-512c-493b-8d3c-741f9d8e4d58"
                },
                {
                    "__changed": false,
                    "__duration": "0s",
                    "__host": "jupiter.lab.example.com",
                    "__number": 4,
                    "__result": "Ok",
                    "__task": "Display managed hosts matching the host pattern",
                    "__task_action": "ansible.builtin.debug",
                    "duration": 0.050906,
                    "end": "2023-03-28T11:01:41.638649",
                    "event_loop": null,
                    "host": "jupiter.lab.example.com",
                    "play": "Resolve host patterns",
                    "play_pattern": "all",
                    "play_uuid": "e244a718-1036-a17e-453c-000000000016",
                    "playbook": "/root/RH294-9.0/projects-host/playbook3.yml",
                    "playbook_uuid": "3e390883-b027-4c8e-b51e-490be5eedb72",
                    "remote_addr": "jupiter.lab.example.com",
                    "res": {
                        "_ansible_no_log": null,
                        "_ansible_verbose_always": true,
                        "changed": false,
                        "msg": "jupiter.lab.example.com"
                    },
                    "resolved_action": "ansible.builtin.debug",
                    "start": "2023-03-28T11:01:41.587743",
                    "task": "Display managed hosts matching the host pattern",
                    "task_action": "ansible.builtin.debug",
                    "task_args": "",
                    "task_path": "/root/RH294-9.0/projects-host/playbook3.yml:6",
                    "task_uuid": "e244a718-1036-a17e-453c-000000000018",
                    "uuid": "71001e0c-bdf9-4176-8596-384abdc9a1f6"
                },
                {
                    "__changed": false,
                    "__duration": "0s",
                    "__host": "saturn.example.com",
                    "__number": 5,
                    "__result": "Ok",
                    "__task": "Display managed hosts matching the host pattern",
                    "__task_action": "ansible.builtin.debug",
                    "duration": 0.05165,
                    "end": "2023-03-28T11:01:41.652634",
                    "event_loop": null,
                    "host": "saturn.example.com",
                    "play": "Resolve host patterns",
                    "play_pattern": "all",
                    "play_uuid": "e244a718-1036-a17e-453c-000000000016",
                    "playbook": "/root/RH294-9.0/projects-host/playbook3.yml",
                    "playbook_uuid": "3e390883-b027-4c8e-b51e-490be5eedb72",
                    "remote_addr": "saturn.example.com",
                    "res": {
                        "_ansible_no_log": null,
                        "_ansible_verbose_always": true,
                        "changed": false,
                        "msg": "saturn.example.com"
                    },
                    "resolved_action": "ansible.builtin.debug",
                    "start": "2023-03-28T11:01:41.600984",
                    "task": "Display managed hosts matching the host pattern",
                    "task_action": "ansible.builtin.debug",
                    "task_args": "",
                    "task_path": "/root/RH294-9.0/projects-host/playbook3.yml:6",
                    "task_uuid": "e244a718-1036-a17e-453c-000000000018",
                    "uuid": "2012c81c-1ad0-4a25-af21-3a0ce09c55d2"
                },
                {
                    "__changed": false,
                    "__duration": "0s",
                    "__host": "db1.example.com",
                    "__number": 6,
                    "__result": "Ok",
                    "__task": "Display managed hosts matching the host pattern",
                    "__task_action": "ansible.builtin.debug",
                    "duration": 0.046895,
                    "end": "2023-03-28T11:01:41.666044",
                    "event_loop": null,
                    "host": "db1.example.com",
                    "play": "Resolve host patterns",
                    "play_pattern": "all",
                    "play_uuid": "e244a718-1036-a17e-453c-000000000016",
                    "playbook": "/root/RH294-9.0/projects-host/playbook3.yml",
                    "playbook_uuid": "3e390883-b027-4c8e-b51e-490be5eedb72",
                    "remote_addr": "db1.example.com",
                    "res": {
                        "_ansible_no_log": null,
                        "_ansible_verbose_always": true,
                        "changed": false,
                        "msg": "db1.example.com"
                    },
                    "resolved_action": "ansible.builtin.debug",
                    "start": "2023-03-28T11:01:41.619149",
                    "task": "Display managed hosts matching the host pattern",
                    "task_action": "ansible.builtin.debug",
                    "task_args": "",
                    "task_path": "/root/RH294-9.0/projects-host/playbook3.yml:6",
                    "task_uuid": "e244a718-1036-a17e-453c-000000000018",
                    "uuid": "dc7bcdbd-9d92-4ea6-ad88-5a3a94ae53e3"
                },
                {
                    "__changed": false,
                    "__duration": "0s",
                    "__host": "db2.example.com",
                    "__number": 7,
                    "__result": "Ok",
                    "__task": "Display managed hosts matching the host pattern",
                    "__task_action": "ansible.builtin.debug",
                    "duration": 0.046688,
                    "end": "2023-03-28T11:01:41.680456",
                    "event_loop": null,
                    "host": "db2.example.com",
                    "play": "Resolve host patterns",
                    "play_pattern": "all",
                    "play_uuid": "e244a718-1036-a17e-453c-000000000016",
                    "playbook": "/root/RH294-9.0/projects-host/playbook3.yml",
                    "playbook_uuid": "3e390883-b027-4c8e-b51e-490be5eedb72",
                    "remote_addr": "db2.example.com",
                    "res": {
                        "_ansible_no_log": null,
                        "_ansible_verbose_always": true,
                        "changed": false,
                        "msg": "db2.example.com"
                    },
                    "resolved_action": "ansible.builtin.debug",
                    "start": "2023-03-28T11:01:41.633768",
                    "task": "Display managed hosts matching the host pattern",
                    "task_action": "ansible.builtin.debug",
                    "task_args": "",
                    "task_path": "/root/RH294-9.0/projects-host/playbook3.yml:6",
                    "task_uuid": "e244a718-1036-a17e-453c-000000000018",
                    "uuid": "087dcaa0-bf82-48e4-8c52-4c084973c9be"
                },
                {
                    "__changed": false,
                    "__duration": "0s",
                    "__host": "db3.example.com",
                    "__number": 8,
                    "__result": "Ok",
                    "__task": "Display managed hosts matching the host pattern",
                    "__task_action": "ansible.builtin.debug",
                    "duration": 0.045894,
                    "end": "2023-03-28T11:01:41.693621",
                    "event_loop": null,
                    "host": "db3.example.com",
                    "play": "Resolve host patterns",
                    "play_pattern": "all",
                    "play_uuid": "e244a718-1036-a17e-453c-000000000016",
                    "playbook": "/root/RH294-9.0/projects-host/playbook3.yml",
                    "playbook_uuid": "3e390883-b027-4c8e-b51e-490be5eedb72",
                    "remote_addr": "db3.example.com",
                    "res": {
                        "_ansible_no_log": null,
                        "_ansible_verbose_always": true,
                        "changed": false,
                        "msg": "db3.example.com"
                    },
                    "resolved_action": "ansible.builtin.debug",
                    "start": "2023-03-28T11:01:41.647727",
                    "task": "Display managed hosts matching the host pattern",
                    "task_action": "ansible.builtin.debug",
                    "task_args": "",
                    "task_path": "/root/RH294-9.0/projects-host/playbook3.yml:6",
                    "task_uuid": "e244a718-1036-a17e-453c-000000000018",
                    "uuid": "50f1bd7e-0d5b-4212-b459-295fc55ba646"
                },
                {
                    "__changed": false,
                    "__duration": "0s",
                    "__host": "lb1.lab.example.com",
                    "__number": 9,
                    "__result": "Ok",
                    "__task": "Display managed hosts matching the host pattern",
                    "__task_action": "ansible.builtin.debug",
                    "duration": 0.04654,
                    "end": "2023-03-28T11:01:41.707737",
                    "event_loop": null,
                    "host": "lb1.lab.example.com",
                    "play": "Resolve host patterns",
                    "play_pattern": "all",
                    "play_uuid": "e244a718-1036-a17e-453c-000000000016",
                    "playbook": "/root/RH294-9.0/projects-host/playbook3.yml",
                    "playbook_uuid": "3e390883-b027-4c8e-b51e-490be5eedb72",
                    "remote_addr": "lb1.lab.example.com",
                    "res": {
                        "_ansible_no_log": null,
                        "_ansible_verbose_always": true,
                        "changed": false,
                        "msg": "lb1.lab.example.com"
                    },
                    "resolved_action": "ansible.builtin.debug",
                    "start": "2023-03-28T11:01:41.661197",
                    "task": "Display managed hosts matching the host pattern",
                    "task_action": "ansible.builtin.debug",
                    "task_args": "",
                    "task_path": "/root/RH294-9.0/projects-host/playbook3.yml:6",
                    "task_uuid": "e244a718-1036-a17e-453c-000000000018",
                    "uuid": "e99b8d38-f289-4349-b09c-9769e7e80ec4"
                },
                {
                    "__changed": false,
                    "__duration": "0s",
                    "__host": "lb2.lab.example.com",
                    "__number": 10,
                    "__result": "Ok",
                    "__task": "Display managed hosts matching the host pattern",
                    "__task_action": "ansible.builtin.debug",
                    "duration": 0.046526,
                    "end": "2023-03-28T11:01:41.722054",
                    "event_loop": null,
                    "host": "lb2.lab.example.com",
                    "play": "Resolve host patterns",
                    "play_pattern": "all",
                    "play_uuid": "e244a718-1036-a17e-453c-000000000016",
                    "playbook": "/root/RH294-9.0/projects-host/playbook3.yml",
                    "playbook_uuid": "3e390883-b027-4c8e-b51e-490be5eedb72",
                    "remote_addr": "lb2.lab.example.com",
                    "res": {
                        "_ansible_no_log": null,
                        "_ansible_verbose_always": true,
                        "changed": false,
                        "msg": "lb2.lab.example.com"
                    },
                    "resolved_action": "ansible.builtin.debug",
                    "start": "2023-03-28T11:01:41.675528",
                    "task": "Display managed hosts matching the host pattern",
                    "task_action": "ansible.builtin.debug",
                    "task_args": "",
                    "task_path": "/root/RH294-9.0/projects-host/playbook3.yml:6",
                    "task_uuid": "e244a718-1036-a17e-453c-000000000018",
                    "uuid": "b4a99112-08a2-4f69-8e2e-082c85ee1914"
                },
                {
                    "__changed": false,
                    "__duration": "0s",
                    "__host": "file1.lab.example.com",
                    "__number": 11,
                    "__result": "Ok",
                    "__task": "Display managed hosts matching the host pattern",
                    "__task_action": "ansible.builtin.debug",
                    "duration": 0.046583,
                    "end": "2023-03-28T11:01:41.735259",
                    "event_loop": null,
                    "host": "file1.lab.example.com",
                    "play": "Resolve host patterns",
                    "play_pattern": "all",
                    "play_uuid": "e244a718-1036-a17e-453c-000000000016",
                    "playbook": "/root/RH294-9.0/projects-host/playbook3.yml",
                    "playbook_uuid": "3e390883-b027-4c8e-b51e-490be5eedb72",
                    "remote_addr": "file1.lab.example.com",
                    "res": {
                        "_ansible_no_log": null,
                        "_ansible_verbose_always": true,
                        "changed": false,
                        "msg": "file1.lab.example.com"
                    },
                    "resolved_action": "ansible.builtin.debug",
                    "start": "2023-03-28T11:01:41.688676",
                    "task": "Display managed hosts matching the host pattern",
                    "task_action": "ansible.builtin.debug",
                    "task_args": "",
                    "task_path": "/root/RH294-9.0/projects-host/playbook3.yml:6",
                    "task_uuid": "e244a718-1036-a17e-453c-000000000018",
                    "uuid": "419e7a7e-8272-466d-aff1-8f74aeb1a275"
                },
                {
                    "__changed": false,
                    "__duration": "0s",
                    "__host": "web1.lab.example.com",
                    "__number": 12,
                    "__result": "Ok",
                    "__task": "Display managed hosts matching the host pattern",
                    "__task_action": "ansible.builtin.debug",
                    "duration": 0.047623,
                    "end": "2023-03-28T11:01:41.749639",
                    "event_loop": null,
                    "host": "web1.lab.example.com",
                    "play": "Resolve host patterns",
                    "play_pattern": "all",
                    "play_uuid": "e244a718-1036-a17e-453c-000000000016",
                    "playbook": "/root/RH294-9.0/projects-host/playbook3.yml",
                    "playbook_uuid": "3e390883-b027-4c8e-b51e-490be5eedb72",
                    "remote_addr": "web1.lab.example.com",
                    "res": {
                        "_ansible_no_log": null,
                        "_ansible_verbose_always": true,
                        "changed": false,
                        "msg": "web1.lab.example.com"
                    },
                    "resolved_action": "ansible.builtin.debug",
                    "start": "2023-03-28T11:01:41.702016",
                    "task": "Display managed hosts matching the host pattern",
                    "task_action": "ansible.builtin.debug",
                    "task_args": "",
                    "task_path": "/root/RH294-9.0/projects-host/playbook3.yml:6",
                    "task_uuid": "e244a718-1036-a17e-453c-000000000018",
                    "uuid": "34bdf796-4e95-48c3-8e23-49f1fcbb1392"
                },
                {
                    "__changed": false,
                    "__duration": "0s",
                    "__host": "file2.example.com",
                    "__number": 13,
                    "__result": "Ok",
                    "__task": "Display managed hosts matching the host pattern",
                    "__task_action": "ansible.builtin.debug",
                    "duration": 0.045793,
                    "end": "2023-03-28T11:01:41.762925",
                    "event_loop": null,
                    "host": "file2.example.com",
                    "play": "Resolve host patterns",
                    "play_pattern": "all",
                    "play_uuid": "e244a718-1036-a17e-453c-000000000016",
                    "playbook": "/root/RH294-9.0/projects-host/playbook3.yml",
                    "playbook_uuid": "3e390883-b027-4c8e-b51e-490be5eedb72",
                    "remote_addr": "file2.example.com",
                    "res": {
                        "_ansible_no_log": null,
                        "_ansible_verbose_always": true,
                        "changed": false,
                        "msg": "file2.example.com"
                    },
                    "resolved_action": "ansible.builtin.debug",
                    "start": "2023-03-28T11:01:41.717132",
                    "task": "Display managed hosts matching the host pattern",
                    "task_action": "ansible.builtin.debug",
                    "task_args": "",
                    "task_path": "/root/RH294-9.0/projects-host/playbook3.yml:6",
                    "task_uuid": "e244a718-1036-a17e-453c-000000000018",
                    "uuid": "6970606c-db69-48f8-842d-7ce225d90bf0"
                },
                {
                    "__changed": false,
                    "__duration": "0s",
                    "__host": "172.25.252.23",
                    "__number": 14,
                    "__result": "Ok",
                    "__task": "Display managed hosts matching the host pattern",
                    "__task_action": "ansible.builtin.debug",
                    "duration": 0.036342,
                    "end": "2023-03-28T11:01:41.766746",
                    "event_loop": null,
                    "host": "172.25.252.23",
                    "play": "Resolve host patterns",
                    "play_pattern": "all",
                    "play_uuid": "e244a718-1036-a17e-453c-000000000016",
                    "playbook": "/root/RH294-9.0/projects-host/playbook3.yml",
                    "playbook_uuid": "3e390883-b027-4c8e-b51e-490be5eedb72",
                    "remote_addr": "172.25.252.23",
                    "res": {
                        "_ansible_no_log": null,
                        "_ansible_verbose_always": true,
                        "changed": false,
                        "msg": "172.25.252.23"
                    },
                    "resolved_action": "ansible.builtin.debug",
                    "start": "2023-03-28T11:01:41.730404",
                    "task": "Display managed hosts matching the host pattern",
                    "task_action": "ansible.builtin.debug",
                    "task_args": "",
                    "task_path": "/root/RH294-9.0/projects-host/playbook3.yml:6",
                    "task_uuid": "e244a718-1036-a17e-453c-000000000018",
                    "uuid": "862fce00-44c7-4523-88ad-ccf0b385e4e5"
                },
                {
                    "__changed": false,
                    "__duration": "0s",
                    "__host": "172.25.252.44",
                    "__number": 15,
                    "__result": "Ok",
                    "__task": "Display managed hosts matching the host pattern",
                    "__task_action": "ansible.builtin.debug",
                    "duration": 0.024099,
                    "end": "2023-03-28T11:01:41.768463",
                    "event_loop": null,
                    "host": "172.25.252.44",
                    "play": "Resolve host patterns",
                    "play_pattern": "all",
                    "play_uuid": "e244a718-1036-a17e-453c-000000000016",
                    "playbook": "/root/RH294-9.0/projects-host/playbook3.yml",
                    "playbook_uuid": "3e390883-b027-4c8e-b51e-490be5eedb72",
                    "remote_addr": "172.25.252.44",
                    "res": {
                        "_ansible_no_log": null,
                        "_ansible_verbose_always": true,
                        "changed": false,
                        "msg": "172.25.252.44"
                    },
                    "resolved_action": "ansible.builtin.debug",
                    "start": "2023-03-28T11:01:41.744364",
                    "task": "Display managed hosts matching the host pattern",
                    "task_action": "ansible.builtin.debug",
                    "task_args": "",
                    "task_path": "/root/RH294-9.0/projects-host/playbook3.yml:6",
                    "task_uuid": "e244a718-1036-a17e-453c-000000000018",
                    "uuid": "d83a7ffa-71d1-468d-97cc-2d1c2fdeca26"
                },
                {
                    "__changed": false,
                    "__duration": "0s",
                    "__host": "172.25.252.32",
                    "__number": 16,
                    "__result": "Ok",
                    "__task": "Display managed hosts matching the host pattern",
                    "__task_action": "ansible.builtin.debug",
                    "duration": 0.022829,
                    "end": "2023-03-28T11:01:41.780892",
                    "event_loop": null,
                    "host": "172.25.252.32",
                    "play": "Resolve host patterns",
                    "play_pattern": "all",
                    "play_uuid": "e244a718-1036-a17e-453c-000000000016",
                    "playbook": "/root/RH294-9.0/projects-host/playbook3.yml",
                    "playbook_uuid": "3e390883-b027-4c8e-b51e-490be5eedb72",
                    "remote_addr": "172.25.252.32",
                    "res": {
                        "_ansible_no_log": null,
                        "_ansible_verbose_always": true,
                        "changed": false,
                        "msg": "172.25.252.32"
                    },
                    "resolved_action": "ansible.builtin.debug",
                    "start": "2023-03-28T11:01:41.758063",
                    "task": "Display managed hosts matching the host pattern",
                    "task_action": "ansible.builtin.debug",
                    "task_args": "",
                    "task_path": "/root/RH294-9.0/projects-host/playbook3.yml:6",
                    "task_uuid": "e244a718-1036-a17e-453c-000000000018",
                    "uuid": "d77d5e95-142f-4a96-a2b7-db9f08193fb7"
                }
            ],
            "uuid": "e244a718-1036-a17e-453c-000000000016"
        }
    ],
    "settings_entries": {
        "ansible-navigator": {
            "ansible": {
                "config": {
                    "help": false
                },
                "doc": {
                    "help": false,
                    "plugin": {
                        "type": "module"
                    }
                },
                "inventory": {
                    "entries": [
                        "/root/RH294-9.0/projects-host/inventory1"
                    ],
                    "help": false
                },
                "playbook": {
                    "help": false,
                    "path": "/root/RH294-9.0/projects-host/playbook3.yml"
                }
            },
            "ansible-builder": {
                "help": false,
                "workdir": "/root/RH294-9.0/projects-host"
            },
            "app": "run",
            "collection-doc-cache-path": "/root/.cache/ansible-navigator/collection_doc_cache.db",
            "color": {
                "enable": true,
                "osc4": true
            },
            "editor": {
                "command": "vi +{line_number} {filename}",
                "console": true
            },
            "exec": {
                "command": "/bin/bash",
                "shell": true
            },
            "execution-environment": {
                "container-engine": "podman",
                "enabled": true,
                "image": "registry.redhat.io/ansible-automation-platform-22/ee-supported-rhel8:latest",
                "pull": {
                    "policy": "tag"
                }
            },
            "images": {
                "details": [
                    "everything"
                ]
            },
            "logging": {
                "append": true,
                "file": "/root/RH294-9.0/projects-host/ansible-navigator.log",
                "level": "warning"
            },
            "mode": "stdout",
            "playbook-artifact": {
                "enable": true,
                "save-as": "{playbook_dir}/{playbook_name}-artifact-{time_stamp}.json"
            },
            "settings": {
                "effective": false,
                "sample": false,
                "schema": "json",
                "sources": false
            },
            "time-zone": "UTC"
        }
    },
    "settings_sources": {
        "ansible-navigator.ansible-builder.help": "Defaults",
        "ansible-navigator.ansible-builder.workdir": "Defaults",
        "ansible-navigator.ansible-lint.config": "Not set",
        "ansible-navigator.ansible-lint.lintables": "Not set",
        "ansible-navigator.ansible-runner.artifact-dir": "Not set",
        "ansible-navigator.ansible-runner.rotate-artifacts-count": "Not set",
        "ansible-navigator.ansible-runner.timeout": "Not set",
        "ansible-navigator.ansible.cmdline": "Not set",
        "ansible-navigator.ansible.config.help": "Defaults",
        "ansible-navigator.ansible.config.path": "Not set",
        "ansible-navigator.ansible.doc.help": "Defaults",
        "ansible-navigator.ansible.doc.plugin.name": "Not set",
        "ansible-navigator.ansible.doc.plugin.type": "Defaults",
        "ansible-navigator.ansible.inventory.entries": "Command line",
        "ansible-navigator.ansible.inventory.help": "Defaults",
        "ansible-navigator.ansible.playbook.help": "Defaults",
        "ansible-navigator.ansible.playbook.path": "Command line",
        "ansible-navigator.app": "Command line",
        "ansible-navigator.collection-doc-cache-path": "Defaults",
        "ansible-navigator.color.enable": "Defaults",
        "ansible-navigator.color.osc4": "Defaults",
        "ansible-navigator.editor.command": "Defaults",
        "ansible-navigator.editor.console": "Defaults",
        "ansible-navigator.exec.command": "Defaults",
        "ansible-navigator.exec.shell": "Defaults",
        "ansible-navigator.execution-environment.container-engine": "Automatically determined",
        "ansible-navigator.execution-environment.container-options": "Not set",
        "ansible-navigator.execution-environment.enabled": "Defaults",
        "ansible-navigator.execution-environment.environment-variables.pass": "Not set",
        "ansible-navigator.execution-environment.environment-variables.set": "Not set",
        "ansible-navigator.execution-environment.image": "Defaults",
        "ansible-navigator.execution-environment.pull.arguments": "Not set",
        "ansible-navigator.execution-environment.pull.policy": "Defaults",
        "ansible-navigator.execution-environment.volume-mounts": "Not set",
        "ansible-navigator.images.details": "Defaults",
        "ansible-navigator.inventory-columns": "Not set",
        "ansible-navigator.logging.append": "Defaults",
        "ansible-navigator.logging.file": "Defaults",
        "ansible-navigator.logging.level": "Defaults",
        "ansible-navigator.mode": "Command line",
        "ansible-navigator.playbook-artifact.enable": "Defaults",
        "ansible-navigator.playbook-artifact.replay": "Not set",
        "ansible-navigator.playbook-artifact.save-as": "Defaults",
        "ansible-navigator.settings.effective": "Defaults",
        "ansible-navigator.settings.sample": "Defaults",
        "ansible-navigator.settings.schema": "Defaults",
        "ansible-navigator.settings.sources": "Defaults",
        "ansible-navigator.time-zone": "Defaults",
        "settings_file_path": "None",
        "settings_file_source": "None"
    },
    "status": "successful",
    "status_color": 10,
    "stdout": [
        "",
        "PLAY [Resolve host patterns] ***************************************************",
        "",
        "TASK [Display managed hosts matching the host pattern] *************************",
        "\u001b[0;32mok: [srv1.example.com] => {\u001b[0m",
        "\u001b[0;32m    \"msg\": \"srv1.example.com\"\u001b[0m",
        "\u001b[0;32m}\u001b[0m",
        "\u001b[0;32mok: [srv2.example.com] => {\u001b[0m",
        "\u001b[0;32m    \"msg\": \"srv2.example.com\"\u001b[0m",
        "\u001b[0;32m}\u001b[0m",
        "\u001b[0;32mok: [s1.lab.example.com] => {\u001b[0m",
        "\u001b[0;32m    \"msg\": \"s1.lab.example.com\"\u001b[0m",
        "\u001b[0;32m}\u001b[0m",
        "\u001b[0;32mok: [s2.lab.example.com] => {\u001b[0m",
        "\u001b[0;32m    \"msg\": \"s2.lab.example.com\"\u001b[0m",
        "\u001b[0;32m}\u001b[0m",
        "\u001b[0;32mok: [jupiter.lab.example.com] => {\u001b[0m",
        "\u001b[0;32m    \"msg\": \"jupiter.lab.example.com\"\u001b[0m",
        "\u001b[0;32m}\u001b[0m",
        "\u001b[0;32mok: [saturn.example.com] => {\u001b[0m",
        "\u001b[0;32m    \"msg\": \"saturn.example.com\"\u001b[0m",
        "\u001b[0;32m}\u001b[0m",
        "\u001b[0;32mok: [db1.example.com] => {\u001b[0m",
        "\u001b[0;32m    \"msg\": \"db1.example.com\"\u001b[0m",
        "\u001b[0;32m}\u001b[0m",
        "\u001b[0;32mok: [db2.example.com] => {\u001b[0m",
        "\u001b[0;32m    \"msg\": \"db2.example.com\"\u001b[0m",
        "\u001b[0;32m}\u001b[0m",
        "\u001b[0;32mok: [db3.example.com] => {\u001b[0m",
        "\u001b[0;32m    \"msg\": \"db3.example.com\"\u001b[0m",
        "\u001b[0;32m}\u001b[0m",
        "\u001b[0;32mok: [lb1.lab.example.com] => {\u001b[0m",
        "\u001b[0;32m    \"msg\": \"lb1.lab.example.com\"\u001b[0m",
        "\u001b[0;32m}\u001b[0m",
        "\u001b[0;32mok: [lb2.lab.example.com] => {\u001b[0m",
        "\u001b[0;32m    \"msg\": \"lb2.lab.example.com\"\u001b[0m",
        "\u001b[0;32m}\u001b[0m",
        "\u001b[0;32mok: [file1.lab.example.com] => {\u001b[0m",
        "\u001b[0;32m    \"msg\": \"file1.lab.example.com\"\u001b[0m",
        "\u001b[0;32m}\u001b[0m",
        "\u001b[0;32mok: [web1.lab.example.com] => {\u001b[0m",
        "\u001b[0;32m    \"msg\": \"web1.lab.example.com\"\u001b[0m",
        "\u001b[0;32m}\u001b[0m",
        "\u001b[0;32mok: [file2.example.com] => {\u001b[0m",
        "\u001b[0;32m    \"msg\": \"file2.example.com\"\u001b[0m",
        "\u001b[0;32m}\u001b[0m",
        "\u001b[0;32mok: [172.25.252.23] => {\u001b[0m",
        "\u001b[0;32m    \"msg\": \"172.25.252.23\"\u001b[0m",
        "\u001b[0;32m}\u001b[0m",
        "\u001b[0;32mok: [172.25.252.44] => {\u001b[0m",
        "\u001b[0;32m    \"msg\": \"172.25.252.44\"\u001b[0m",
        "\u001b[0;32m}\u001b[0m",
        "\u001b[0;32mok: [172.25.252.32] => {\u001b[0m",
        "\u001b[0;32m    \"msg\": \"172.25.252.32\"\u001b[0m",
        "\u001b[0;32m}\u001b[0m",
        "",
        "PLAY RECAP *********************************************************************",
        "\u001b[0;32m172.25.252.23\u001b[0m              : \u001b[0;32mok=1   \u001b[0m changed=0    unreachable=0    failed=0    skipped=0    rescued=0    ignored=0   ",
        "\u001b[0;32m172.25.252.32\u001b[0m              : \u001b[0;32mok=1   \u001b[0m changed=0    unreachable=0    failed=0    skipped=0    rescued=0    ignored=0   ",
        "\u001b[0;32m172.25.252.44\u001b[0m              : \u001b[0;32mok=1   \u001b[0m changed=0    unreachable=0    failed=0    skipped=0    rescued=0    ignored=0   ",
        "\u001b[0;32mdb1.example.com\u001b[0m            : \u001b[0;32mok=1   \u001b[0m changed=0    unreachable=0    failed=0    skipped=0    rescued=0    ignored=0   ",
        "\u001b[0;32mdb2.example.com\u001b[0m            : \u001b[0;32mok=1   \u001b[0m changed=0    unreachable=0    failed=0    skipped=0    rescued=0    ignored=0   ",
        "\u001b[0;32mdb3.example.com\u001b[0m            : \u001b[0;32mok=1   \u001b[0m changed=0    unreachable=0    failed=0    skipped=0    rescued=0    ignored=0   ",
        "\u001b[0;32mfile1.lab.example.com\u001b[0m      : \u001b[0;32mok=1   \u001b[0m changed=0    unreachable=0    failed=0    skipped=0    rescued=0    ignored=0   ",
        "\u001b[0;32mfile2.example.com\u001b[0m          : \u001b[0;32mok=1   \u001b[0m changed=0    unreachable=0    failed=0    skipped=0    rescued=0    ignored=0   ",
        "\u001b[0;32mjupiter.lab.example.com\u001b[0m    : \u001b[0;32mok=1   \u001b[0m changed=0    unreachable=0    failed=0    skipped=0    rescued=0    ignored=0   ",
        "\u001b[0;32mlb1.lab.example.com\u001b[0m        : \u001b[0;32mok=1   \u001b[0m changed=0    unreachable=0    failed=0    skipped=0    rescued=0    ignored=0   ",
        "\u001b[0;32mlb2.lab.example.com\u001b[0m        : \u001b[0;32mok=1   \u001b[0m changed=0    unreachable=0    failed=0    skipped=0    rescued=0    ignored=0   ",
        "\u001b[0;32ms1.lab.example.com\u001b[0m         : \u001b[0;32mok=1   \u001b[0m changed=0    unreachable=0    failed=0    skipped=0    rescued=0    ignored=0   ",
        "\u001b[0;32ms2.lab.example.com\u001b[0m         : \u001b[0;32mok=1   \u001b[0m changed=0    unreachable=0    failed=0    skipped=0    rescued=0    ignored=0   ",
        "\u001b[0;32msaturn.example.com\u001b[0m         : \u001b[0;32mok=1   \u001b[0m changed=0    unreachable=0    failed=0    skipped=0    rescued=0    ignored=0   ",
        "\u001b[0;32msrv1.example.com\u001b[0m           : \u001b[0;32mok=1   \u001b[0m changed=0    unreachable=0    failed=0    skipped=0    rescued=0    ignored=0   ",
        "\u001b[0;32msrv2.example.com\u001b[0m           : \u001b[0;32mok=1   \u001b[0m changed=0    unreachable=0    failed=0    skipped=0    rescued=0    ignored=0   ",
        "\u001b[0;32mweb1.lab.example.com\u001b[0m       : \u001b[0;32mok=1   \u001b[0m changed=0    unreachable=0    failed=0    skipped=0    rescued=0    ignored=0   "
    ],
    "version": "2.0.0"
}
